mlconfound/__init__.py
mlconfound/_utils.py
mlconfound/plot.py
mlconfound/simulate.py
mlconfound/stats.py
mlconfound-0.21.3.dist-info/METADATA
mlconfound-0.21.3.dist-info/LICENSE
mlconfound-0.21.3.dist-info/WHEEL
mlconfound-0.21.3.dist-info/RECORD
